[
    {
        "title": "Group 1",
        "icon": "component",
        "services": [
            {
                "title": "Service 1",
                "url": "https://example.com",
                "logo-path": "%PUBLIC_URL%/logos/1.png"
            },
            {
                "title": "GitHub",
                "url": "https://github.com/apicomplexa",
                "logo-path": "https://github.githubassets.com/favicons/favicon-dark.svg"
            }
        ]
    },{
        "title": "Group 2",
        "icon": "grid-2x2",
        "services": [
            {
                "title": "Service 1",
                "url": "https://example.com",
                "logo-path": "%PUBLIC_URL%/logos/1.png"
            },
            {
                "title": "GitHub",
                "url": "https://github.com/apicomplexa",
                "logo-path": "https://github.githubassets.com/favicons/favicon-dark.svg"
            }
        ]
    },{
        "title": "Group 3",
        "icon": "x",
        "services": []
    }
]